MANIFEST.in
README.rst
setup.py
examples/__init__.py
examples/authorize_net.py
examples/firstdata.py
examples/innovative_gw.py
examples/plugnpay.py
examples/samurai_ex.py
examples/stripe_ex.py
paython/__init__.py
paython/exceptions.py
paython.egg-info/PKG-INFO
paython.egg-info/SOURCES.txt
paython.egg-info/dependency_links.txt
paython.egg-info/requires.txt
paython.egg-info/top_level.txt
paython/django/__init__.py
paython/django/forms.py
paython/gateways/__init__.py
paython/gateways/authorize_net.py
paython/gateways/core.py
paython/gateways/firstdata_legacy.py
paython/gateways/innovative_gw.py
paython/gateways/plugnpay.py
paython/gateways/samurai_ff.py
paython/gateways/stripe_com.py
paython/keys/__init__.py
paython/lib/__init__.py
paython/lib/api.py
paython/lib/cc.py
paython/lib/utils.py
tests/__init__.py
tests/test_credit_card.py
tests/test_example.py
tests/test_exceptions.py
tests/test_utils.py