Metadata-Version: 1.1
Name: paython
Version: 0.0.3
Summary: Trying to make it easy to accept payments in Python.
Home-page: https://github.com/abunsen/Paython
Author: Auston Bunsen, Igor Guerrero
Author-email: auston.bunsen@gmail.com
License: MIT
Keywords: payments gateways creditcards processing
Platform: UNKNOWN
Classifier: Development Status :: 2 - Pre-Alpha
Classifier: Intended Audience :: Developers
Classifier: Intended Audience :: Financial and Insurance Industry
Classifier: Natural Language :: English
Classifier: Operating System :: POSIX
Classifier: Programming Language :: Python :: 2.6
Classifier: Topic :: Office/Business :: Financial
Classifier: License :: OSI Approved :: MIT License
